markdown_to_mrkdwn/__init__.py
markdown_to_mrkdwn/converter.py
markdown_to_mrkdwn-0.3.1.dist-info/licenses/LICENSE
tests/__init__.py
tests/test_converter.py
markdown_to_mrkdwn-0.3.1.dist-info/METADATA
markdown_to_mrkdwn-0.3.1.dist-info/WHEEL
markdown_to_mrkdwn-0.3.1.dist-info/top_level.txt
markdown_to_mrkdwn-0.3.1.dist-info/RECORD
