Metadata-Version: 2.4
Name: markdown_to_mrkdwn
Version: 0.3.1
Summary: A library to convert Markdown to Slack's mrkdwn format
Home-page: https://github.com/fla9ua/markdown_to_mrkdwn
Download-URL: https://github.com/fla9ua/markdown_to_mrkdwn
Author: fla9ua
Author-email: fla9ua@gmail.com
License: MIT License
Classifier: Programming Language :: Python :: 3
Classifier: License :: OSI Approved :: MIT License
Classifier: Operating System :: OS Independent
Requires-Python: >=3.6
License-File: LICENSE
Dynamic: author
Dynamic: author-email
Dynamic: classifier
Dynamic: description
Dynamic: description-content-type
Dynamic: download-url
Dynamic: home-page
Dynamic: license
Dynamic: license-file
Dynamic: requires-python
Dynamic: summary
